[
  {
    "id": "d10e8400-e29b-41d4-a716-446655440600",
    "internal_code": "SVC-001",
    "name": "Jornada Técnico General",
    "description": "Servicio de técnico para jornada completa (8 horas). Incluye desplazamiento, montaje, configuración y desmontaje de equipos audiovisuales.",
    "type": "servicio",
    "subtype": "mano_de_obra",
    "category_id": "c10e8400-e29b-41d4-a716-446655440500",
    "base_price": 280.00,
    "cost_price": 0.00,
    "is_stockable": false,
    "stock_current": null,
    "stock_min": null,
    "unit": "día",
    "is_active": true,
    "created_at": "2025-01-21T00:00:00Z",
    "updated_at": "2025-01-21T00:00:00Z"
  },
  {
    "id": "d20e8400-e29b-41d4-a716-446655440610",
    "internal_code": "SVC-002",
    "name": "Hora Extra General",
    "description": "Servicio de técnico por hora adicional. Aplicable cuando se supera la jornada estándar o se requiere asistencia técnica fuera del horario pactado.",
    "type": "servicio",
    "subtype": "mano_de_obra",
    "category_id": "c10e8400-e29b-41d4-a716-446655440500",
    "base_price": 35.00,
    "cost_price": 0.00,
    "is_stockable": false,
    "stock_current": null,
    "stock_min": null,
    "unit": "hora",
    "is_active": true,
    "created_at": "2025-01-21T00:00:00Z",
    "updated_at": "2025-01-21T00:00:00Z"
  },
  {
    "id": "d30e8400-e29b-41d4-a716-446655440620",
    "internal_code": "SVC-003",
    "name": "Dieta Completa",
    "description": "Dieta completa para desplazamientos que requieren pernoctación o jornadas superiores a 8 horas. Incluye desayuno, comida y cena.",
    "type": "servicio",
    "subtype": "logistica",
    "category_id": "c20e8400-e29b-41d4-a716-446655440510",
    "base_price": 40.00,
    "cost_price": 0.00,
    "is_stockable": false,
    "stock_current": null,
    "stock_min": null,
    "unit": "unidad",
    "is_active": true,
    "created_at": "2025-01-21T00:00:00Z",
    "updated_at": "2025-01-21T00:00:00Z"
  },
  {
    "id": "d40e8400-e29b-41d4-a716-446655440630",
    "internal_code": "SVC-004",
    "name": "Media Dieta",
    "description": "Media dieta para desplazamientos de media jornada o que no requieren pernoctación. Incluye comida principal del día.",
    "type": "servicio",
    "subtype": "logistica",
    "category_id": "c20e8400-e29b-41d4-a716-446655440510",
    "base_price": 20.00,
    "cost_price": 0.00,
    "is_stockable": false,
    "stock_current": null,
    "stock_min": null,
    "unit": "unidad",
    "is_active": true,
    "created_at": "2025-01-21T00:00:00Z",
    "updated_at": "2025-01-21T00:00:00Z"
  },
  {
    "id": "d50e8400-e29b-41d4-a716-446655440640",
    "internal_code": "SVC-005",
    "name": "Kilometraje",
    "description": "Compensación por desplazamiento en vehículo propio. Se aplica por kilómetro recorrido desde el punto de origen hasta el lugar de trabajo y regreso.",
    "type": "servicio",
    "subtype": "logistica",
    "category_id": "c20e8400-e29b-41d4-a716-446655440510",
    "base_price": 0.40,
    "cost_price": 0.00,
    "is_stockable": false,
    "stock_current": null,
    "stock_min": null,
    "unit": "km",
    "is_active": true,
    "created_at": "2025-01-21T00:00:00Z",
    "updated_at": "2025-01-21T00:00:00Z"
  },
  {
    "id": "d60e8400-e29b-41d4-a716-446655440650",
    "internal_code": "PROD-001",
    "name": "Cabinet LED ALS P2.604 indoor 1000x500mm (con módulos)",
    "description": "Cabinet LED ALS P2.604 para interior, formato 1000x500mm. Incluye 8 módulos LED. Ideal para pantallas de gran formato en eventos y espacios interiores.",
    "type": "producto",
    "subtype": "alquiler",
    "category_id": "c30e8400-e29b-41d4-a716-446655440520",
    "primary_supplier_id": "990e8400-e29b-41d4-a716-446655440130",
    "base_price": 803.50,
    "cost_price": 242.00,
    "margin_percentage": 232.02,
    "rental_price_12m": 66.96,
    "rental_price_18m": 40.18,
    "rental_price_daily": 28.70,
    "is_stockable": true,
    "stock_current": 0,
    "stock_min": 0,
    "unit": "unidad",
    "is_active": true,
    "created_at": "2025-01-21T00:00:00Z",
    "updated_at": "2025-01-21T00:00:00Z"
  },
  {
    "id": "d70e8400-e29b-41d4-a716-446655440660",
    "internal_code": "PROD-002",
    "name": "Cabinet LED ALS P2.604 indoor 1000x500mm (sin módulos)",
    "description": "Cabinet LED ALS P2.604 para interior, formato 1000x500mm sin módulos. Estructura base para montaje de pantallas LED modulares.",
    "type": "producto",
    "subtype": "alquiler",
    "category_id": "c30e8400-e29b-41d4-a716-446655440520",
    "primary_supplier_id": "990e8400-e29b-41d4-a716-446655440130",
    "base_price": 299.66,
    "cost_price": 42.00,
    "margin_percentage": 613.48,
    "rental_price_12m": 24.97,
    "rental_price_18m": 14.98,
    "rental_price_daily": 10.70,
    "is_stockable": true,
    "stock_current": 0,
    "stock_min": 0,
    "unit": "unidad",
    "is_active": true,
    "created_at": "2025-01-21T00:00:00Z",
    "updated_at": "2025-01-21T00:00:00Z"
  },
  {
    "id": "d80e8400-e29b-41d4-a716-446655440670",
    "internal_code": "PROD-003",
    "name": "Módulo LS P2.604 250x250 mm",
    "description": "Módulo LED LS P2.604 de 250x250mm. Módulo individual para pantallas LED modulares. Pitch 2.604mm, alta resolución para interiores.",
    "type": "producto",
    "subtype": "alquiler",
    "category_id": "c30e8400-e29b-41d4-a716-446655440520",
    "primary_supplier_id": "990e8400-e29b-41d4-a716-446655440130",
    "base_price": 62.98,
    "cost_price": 25.00,
    "margin_percentage": 151.92,
    "rental_price_12m": 5.25,
    "rental_price_18m": 3.15,
    "rental_price_daily": 2.25,
    "is_stockable": true,
    "stock_current": 0,
    "stock_min": 0,
    "unit": "unidad",
    "is_active": true,
    "created_at": "2025-01-21T00:00:00Z",
    "updated_at": "2025-01-21T00:00:00Z"
  },
  {
    "id": "d90e8400-e29b-41d4-a716-446655440680",
    "internal_code": "PROD-004",
    "name": "Receiving MRV412-N",
    "description": "Receptor de señal MRV412-N para sistemas de video. Compatible con pantallas LED y sistemas de procesamiento de video.",
    "type": "producto",
    "subtype": "alquiler",
    "category_id": "c30e8400-e29b-41d4-a716-446655440520",
    "primary_supplier_id": "990e8400-e29b-41d4-a716-446655440130",
    "base_price": 35.20,
    "cost_price": 22.00,
    "margin_percentage": 60.00,
    "rental_price_12m": 2.93,
    "rental_price_18m": 1.76,
    "rental_price_daily": 1.26,
    "is_stockable": true,
    "stock_current": 0,
    "stock_min": 0,
    "unit": "unidad",
    "is_active": true,
    "created_at": "2025-01-21T00:00:00Z",
    "updated_at": "2025-01-21T00:00:00Z"
  },
  {
    "id": "da0e8400-e29b-41d4-a716-446655440690",
    "internal_code": "PROD-005",
    "name": "Video Procesador TB-50 con player incluido",
    "description": "Procesador de video TB-50 con reproductor integrado. Sistema completo para control y procesamiento de señales de video en pantallas LED y sistemas de visualización.",
    "type": "producto",
    "subtype": "alquiler",
    "category_id": "c30e8400-e29b-41d4-a716-446655440520",
    "primary_supplier_id": "990e8400-e29b-41d4-a716-446655440130",
    "base_price": 562.34,
    "cost_price": 346.00,
    "margin_percentage": 62.53,
    "rental_price_12m": 46.86,
    "rental_price_18m": 28.12,
    "rental_price_daily": 20.08,
    "is_stockable": true,
    "stock_current": 0,
    "stock_min": 0,
    "unit": "unidad",
    "is_active": true,
    "created_at": "2025-01-21T00:00:00Z",
    "updated_at": "2025-01-21T00:00:00Z"
  },
  {
    "id": "db0e8400-e29b-41d4-a716-446655440700",
    "internal_code": "SVC-006",
    "name": "Gestión de Contenidos",
    "description": "Servicio mensual de gestión y actualización de contenidos para pantallas LED. Incluye diseño, programación y actualización de contenidos visuales.",
    "type": "servicio",
    "subtype": "alquiler",
    "category_id": "c30e8400-e29b-41d4-a716-446655440520",
    "base_price": 85.00,
    "cost_price": 0.00,
    "is_stockable": false,
    "stock_current": null,
    "stock_min": null,
    "unit": "mes",
    "is_active": true,
    "created_at": "2025-01-21T00:00:00Z",
    "updated_at": "2025-01-21T00:00:00Z"
  }
]
